srsinst/rga/__init__.py
srsinst/rga/__main__.py
srsinst/rga/gaslib.dat
srsinst/rga/rga.taskconfig
srsinst/rga/instruments/__init__.py
srsinst/rga/instruments/get_instruments.py
srsinst/rga/instruments/rga100/__init__.py
srsinst/rga/instruments/rga100/commands.py
srsinst/rga/instruments/rga100/components.py
srsinst/rga/instruments/rga100/errors.py
srsinst/rga/instruments/rga100/rga.py
srsinst/rga/instruments/rga100/rga_commands.json
srsinst/rga/instruments/rga100/scans.py
srsinst/rga/instruments/rga100/sicp.py
srsinst/rga/plots/__init__.py
srsinst/rga/plots/analogscanplot.py
srsinst/rga/plots/analysis.py
srsinst/rga/plots/basescanplot.py
srsinst/rga/plots/histogramscanplot.py
srsinst/rga/plots/timeplot.py
srsinst/rga/tasks/__init__.py
srsinst/rga/tasks/analogscantask.py
srsinst/rga/tasks/cemcontroltask.py
srsinst/rga/tasks/cemgaintask.py
srsinst/rga/tasks/compositionanalysistask.py
srsinst/rga/tasks/derivedpvstscantask.py
srsinst/rga/tasks/filamentcontroltask.py
srsinst/rga/tasks/histogramscantask.py
srsinst/rga/tasks/peaktuningtask.py
srsinst/rga/tasks/pvstscantask.py
srsinst/rga/tasks/searchlan.py
srsinst_rga-0.3.8.dist-info/LICENSE
srsinst_rga-0.3.8.dist-info/METADATA
srsinst_rga-0.3.8.dist-info/WHEEL
srsinst_rga-0.3.8.dist-info/entry_points.txt
srsinst_rga-0.3.8.dist-info/top_level.txt
srsinst_rga-0.3.8.dist-info/RECORD
