Metadata-Version: 2.1
Name: srsinst.rga
Version: 0.3.8
Summary: Instrument driver package for Residual Gas Analyzers (RGA) from Stanford Research Systems
Author: Chulhoon Kim
License: MIT license
Project-URL: homepage, https://github.com/thinkSRS/srsinst.rga
Project-URL: repository, https://github.com/thinkSRS/srsinst.rga.git
Project-URL: documentation, https://thinksrs.github.io/srsinst.rga
Keywords: RGA,residual gas analyzer,SRS,Stanford Research Systems
Classifier: Development Status :: 4 - Beta
Classifier: Intended Audience :: Science/Research
Classifier: License :: OSI Approved :: MIT License
Classifier: Programming Language :: Python :: 3.7
Classifier: Programming Language :: Python :: 3.8
Classifier: Programming Language :: Python :: 3.9
Classifier: Programming Language :: Python :: 3.10
Classifier: Topic :: Scientific/Engineering
Requires-Python: >=3.7
License-File: LICENSE
Requires-Dist: numpy
Requires-Dist: scipy <1.15,>=1.0
Requires-Dist: srsgui >=0.4.3
Provides-Extra: docs
Requires-Dist: matplotlib ; extra == 'docs'
Requires-Dist: pyside2 ; extra == 'docs'
Requires-Dist: sphinx >=5 ; extra == 'docs'
Requires-Dist: sphinx-rtd-theme >=1 ; extra == 'docs'
Provides-Extra: full
Requires-Dist: matplotlib >=3.6.2 ; extra == 'full'
Requires-Dist: pyside6 ; extra == 'full'
